photoscript/__init__.py
photoscript/__main__.py
photoscript/_version.py
photoscript/exceptions.py
photoscript/photoscript.applescript
photoscript/script_loader.py
photoscript/utils.py
photoscript-0.5.2.dist-info/licenses/LICENSE
photoscript-0.5.2.dist-info/METADATA
photoscript-0.5.2.dist-info/WHEEL
photoscript-0.5.2.dist-info/top_level.txt
photoscript-0.5.2.dist-info/RECORD
