Metadata-Version: 2.4
Name: photoscript
Version: 0.5.2
Summary: Python wrapper around Apple Photos applescript interface
Author-email: Rhet Turnbull <rturnbull+git@gmail.com>
License: MIT License
Project-URL: Homepage, https://github.com/RhetTbull/photoscript
Project-URL: Repository, https://github.com/RhetTbull/photoscript
Keywords: photos,mac,macos,applescript,apple
Classifier: Development Status :: 5 - Production/Stable
Classifier: Environment :: MacOS X
Classifier: Intended Audience :: Developers
Classifier: License :: OSI Approved :: MIT License
Classifier: Operating System :: MacOS :: MacOS X
Classifier: Programming Language :: Python :: 3.10
Classifier: Programming Language :: Python :: 3.11
Classifier: Programming Language :: Python :: 3.12
Classifier: Programming Language :: Python :: 3.13
Classifier: Topic :: Software Development :: Libraries :: Python Modules
Requires-Python: <4.0,>=3.10
License-File: LICENSE
Requires-Dist: pyobjc-core>=9.2
Requires-Dist: pyobjc-framework-Cocoa>=9.2
Requires-Dist: pyobjc-framework-AppleScriptKit>=9.2
Requires-Dist: pyobjc-framework-AppleScriptObjC>=9.2
Requires-Dist: py-applescript>=1.0.3
Requires-Dist: tenacity<9.0.0,>=8.0.1
Provides-Extra: dev
Requires-Dist: setuptools; extra == "dev"
Requires-Dist: pytest<8.0,>=7.1.3; extra == "dev"
Requires-Dist: flaky<4.0,>=3.7.0; extra == "dev"
Requires-Dist: wheel>=0.37.1; extra == "dev"
Requires-Dist: build>=0.8.0; extra == "dev"
Requires-Dist: twine>=4.0.1; extra == "dev"
Requires-Dist: bump2version>=1.0.1; extra == "dev"
Requires-Dist: mkdocs>=1.4.2; extra == "dev"
Requires-Dist: mkdocs-material>=9.0.13; extra == "dev"
Requires-Dist: mkdocstrings-python>=0.8.3; extra == "dev"
Requires-Dist: tenacity<9.0.0,>=8.0.1; extra == "dev"
Dynamic: license-file
